seroup/__init__.py
seroup/commands/__init__.py
seroup/commands/base.py
seroup/commands/disable.py
seroup/commands/download.py
seroup/commands/enable.py
seroup/commands/init.py
seroup/commands/registration.py
seroup/commands/teardown.py
seroup/commands/ucors.py
seroup/commands/upload.py
seroup/configuration/__init__.py
seroup/configuration/config.py
seroup/run.py
seroup-0.2.6.dist-info/LICENSE
seroup-0.2.6.dist-info/METADATA
seroup-0.2.6.dist-info/WHEEL
seroup-0.2.6.dist-info/entry_points.txt
seroup-0.2.6.dist-info/RECORD
