Metadata-Version: 2.1
Name: seroup
Version: 0.2.6
Summary: CLI tool to manage sero servers
Author: clowzed
Author-email: clowzed.work@gmail.com
Requires-Python: >=3.12,<4.0
Classifier: Programming Language :: Python :: 3
Classifier: Programming Language :: Python :: 3.12
Requires-Dist: dacite (>=1.8.1,<2.0.0)
Requires-Dist: requests (>=2.32.3,<3.0.0)
Requires-Dist: seroapi (>=0.2.6,<0.3.0)
Requires-Dist: toml (>=0.10.2,<0.11.0)
